{
  "url": "https://www.chordie.com/chord.pere/www.gitaartabs.nl/chords/3js/je-vecht-nooit-alleen",
  "title": "Je Vecht Nooit Alleen",
  "artist": "3JS",
  "key": null,
  "scrapedAt": "2026-02-14T20:45:42.282Z",
  "sections": [
    {
      "name": "Verse",
      "lines": [
        {
          "chunks": [
            {
              "chord": null,
              "lyrics": "> 3JS - Je Vecht Nooit Alleen"
            }
          ]
        },
        {
          "chunks": [
            {
              "chord": null,
              "lyrics": "Intro"
            }
          ]
        },
        {
          "chunks": [
            {
              "chord": null,
              "lyrics": "Couplet"
            }
          ]
        },
        {
          "chunks": [
            {
              "chord": null,
              "lyrics": "Refrein"
            }
          ]
        },
        {
          "chunks": [
            {
              "chord": null,
              "lyrics": "Couplet"
            }
          ]
        }
      ]
    }
  ]
}
