{
  "url": "https://www.chordie.com/chord.pere/www.theguitarguy.com/imbeginn.htm",
  "title": "I'm Beginning To See The Light",
  "artist": "",
  "key": null,
  "scrapedAt": "2026-02-14T18:03:08.165Z",
  "sections": [
    {
      "name": "Verse",
      "lines": [
        {
          "chunks": [
            {
              "chord": null,
              "lyrics": "I"
            },
            {
              "chord": "D6",
              "lyrics": "never cared"
            },
            {
              "chord": "Fdim",
              "lyrics": "much"
            },
            {
              "chord": "A7",
              "lyrics": "for"
            },
            {
              "chord": "D",
              "lyrics": "moonlit s"
            },
            {
              "chord": "D6",
              "lyrics": "kies,"
            }
          ]
        },
        {
          "chunks": [
            {
              "chord": null,
              "lyrics": "I"
            },
            {
              "chord": "Dm6",
              "lyrics": "never wink"
            },
            {
              "chord": "G6",
              "lyrics": "back at"
            },
            {
              "chord": "Dm6",
              "lyrics": "fire f"
            },
            {
              "chord": "Gm7",
              "lyrics": "lies,"
            }
          ]
        },
        {
          "chunks": [
            {
              "chord": null,
              "lyrics": "But n"
            },
            {
              "chord": "D",
              "lyrics": "ow that the s"
            },
            {
              "chord": "F#m",
              "lyrics": "tars are"
            },
            {
              "chord": "B7",
              "lyrics": "in you eyes,"
            }
          ]
        },
        {
          "chunks": [
            {
              "chord": null,
              "lyrics": "I'm be"
            },
            {
              "chord": "G/B",
              "lyrics": "ginning to"
            },
            {
              "chord": "A7",
              "lyrics": "see"
            },
            {
              "chord": "A7+5",
              "lyrics": "the l"
            },
            {
              "chord": "D",
              "lyrics": "ight."
            },
            {
              "chord": "A7",
              "lyrics": ""
            }
          ]
        },
        {
          "chunks": [
            {
              "chord": "D6",
              "lyrics": "I never went"
            },
            {
              "chord": "Fdim",
              "lyrics": "in"
            },
            {
              "chord": "A7",
              "lyrics": "for"
            },
            {
              "chord": "D",
              "lyrics": "aftergl"
            },
            {
              "chord": "D6",
              "lyrics": "ow"
            }
          ]
        },
        {
          "chunks": [
            {
              "chord": null,
              "lyrics": "Or"
            },
            {
              "chord": "Dm6",
              "lyrics": "candlelight"
            },
            {
              "chord": "G6",
              "lyrics": "on the m"
            },
            {
              "chord": "Dm6",
              "lyrics": "istle"
            },
            {
              "chord": "Gm7",
              "lyrics": "toe,"
            }
          ]
        },
        {
          "chunks": [
            {
              "chord": null,
              "lyrics": "But"
            },
            {
              "chord": "D",
              "lyrics": "now when you"
            },
            {
              "chord": "F#m",
              "lyrics": "turn the"
            },
            {
              "chord": "B7",
              "lyrics": "lamp down low,"
            }
          ]
        },
        {
          "chunks": [
            {
              "chord": null,
              "lyrics": "I'm beg"
            },
            {
              "chord": "G/B",
              "lyrics": "inning to s"
            },
            {
              "chord": "A7",
              "lyrics": "ee t"
            },
            {
              "chord": "A7+5",
              "lyrics": "he lig"
            },
            {
              "chord": "D",
              "lyrics": "ht."
            }
          ]
        },
        {
          "chunks": [
            {
              "chord": null,
              "lyrics": "Bridge:"
            }
          ]
        },
        {
          "chunks": [
            {
              "chord": "F#7",
              "lyrics": "Used to ramble through the park"
            }
          ]
        },
        {
          "chunks": [
            {
              "chord": "F7",
              "lyrics": "Shadow boxing in the dark;"
            }
          ]
        },
        {
          "chunks": [
            {
              "chord": "E7",
              "lyrics": "Then you came and caused a spark"
            }
          ]
        },
        {
          "chunks": [
            {
              "chord": null,
              "lyrics": "That's a f"
            },
            {
              "chord": "Bb7",
              "lyrics": "our-alarm fire n"
            },
            {
              "chord": "A7",
              "lyrics": "ow."
            }
          ]
        },
        {
          "chunks": [
            {
              "chord": "D6",
              "lyrics": "I never made"
            },
            {
              "chord": "Fdim",
              "lyrics": "love"
            },
            {
              "chord": "A7",
              "lyrics": "by l"
            },
            {
              "chord": "D",
              "lyrics": "antern s"
            },
            {
              "chord": "D6",
              "lyrics": "hine,"
            }
          ]
        },
        {
          "chunks": [
            {
              "chord": null,
              "lyrics": "I"
            },
            {
              "chord": "Dm6",
              "lyrics": "never saw r"
            },
            {
              "chord": "G6",
              "lyrics": "ainbows"
            },
            {
              "chord": "Dm6",
              "lyrics": "in my"
            },
            {
              "chord": "Gm7",
              "lyrics": "wine,"
            }
          ]
        },
        {
          "chunks": [
            {
              "chord": null,
              "lyrics": "But"
            },
            {
              "chord": "D",
              "lyrics": "now that your"
            },
            {
              "chord": "F#m",
              "lyrics": "lips are"
            },
            {
              "chord": "B7",
              "lyrics": "burning mine,"
            }
          ]
        },
        {
          "chunks": [
            {
              "chord": null,
              "lyrics": "I'm be"
            },
            {
              "chord": "G/B",
              "lyrics": "ginning to"
            },
            {
              "chord": "A7",
              "lyrics": "see"
            },
            {
              "chord": "A7+5",
              "lyrics": "the li"
            },
            {
              "chord": "D",
              "lyrics": "ght."
            }
          ]
        }
      ]
    }
  ]
}
