{
  "url": "https://www.chordie.com/chord.pere/www.guitartabs.cc/tabs/j/jason_aldean/just_passing_through_tab.html",
  "title": "Just Passing Through",
  "artist": "Jason Aldean",
  "key": null,
  "scrapedAt": "2026-02-14T21:23:53.274Z",
  "sections": [
    {
      "name": "Verse",
      "lines": [
        {
          "chunks": [
            {
              "chord": null,
              "lyrics": "A little bit of distortion for this song wouldnt hurt ;)"
            }
          ]
        },
        {
          "chunks": [
            {
              "chord": null,
              "lyrics": "The riff and solo seem to branch off from the intro. sounds pretty cool though..."
            }
          ]
        },
        {
          "chunks": [
            {
              "chord": null,
              "lyrics": "of course it would, its a Jason Aldean song lol"
            }
          ]
        },
        {
          "chunks": [
            {
              "chord": null,
              "lyrics": "The intro can also be played on the G string the same way,"
            }
          ]
        },
        {
          "chunks": [
            {
              "chord": null,
              "lyrics": "just starting on the second fret. If you'd rather play it that way, go for it . Have fun everybody"
            }
          ]
        },
        {
          "chunks": [
            {
              "chord": null,
              "lyrics": "Palm mute all the chords for the first verse."
            }
          ]
        },
        {
          "chunks": [
            {
              "chord": "D",
              "lyrics": "I can hear that rooster crowing down the road"
            }
          ]
        },
        {
          "chunks": [
            {
              "chord": "A",
              "lyrics": "I felt my eyes open up real slow"
            }
          ]
        },
        {
          "chunks": [
            {
              "chord": "Bm",
              "lyrics": "and I looked around"
            }
          ]
        },
        {
          "chunks": [
            {
              "chord": "G",
              "lyrics": "making sure I hadnt checked out"
            }
          ]
        },
        {
          "chunks": [
            {
              "chord": "D",
              "lyrics": "cause there was an angel lying next to me"
            }
          ]
        },
        {
          "chunks": [
            {
              "chord": "A",
              "lyrics": "and I figured heavens where I must be"
            }
          ]
        },
        {
          "chunks": [
            {
              "chord": "Bm",
              "lyrics": "oh but it was you"
            }
          ]
        },
        {
          "chunks": [
            {
              "chord": "G",
              "lyrics": "baby what else could I do"
            },
            {
              "chord": "G",
              "lyrics": ""
            },
            {
              "chord": "G/F#",
              "lyrics": ""
            }
          ]
        },
        {
          "chunks": [
            {
              "chord": "Bm",
              "lyrics": "in that bed I said a little prayer"
            }
          ]
        },
        {
          "chunks": [
            {
              "chord": "G",
              "lyrics": "for one more day"
            },
            {
              "chord": "A",
              "lyrics": "I'm still here"
            }
          ]
        },
        {
          "chunks": [
            {
              "chord": "D",
              "lyrics": "It's your world and I'm just in it"
            }
          ]
        },
        {
          "chunks": [
            {
              "chord": "A",
              "lyrics": "Aint no other way to spin it,"
            }
          ]
        },
        {
          "chunks": [
            {
              "chord": "Bm",
              "lyrics": "Lucky me just being there when I get to ho"
            },
            {
              "chord": "G",
              "lyrics": "ld you"
            }
          ]
        },
        {
          "chunks": [
            {
              "chord": "Bm",
              "lyrics": "I'm just here to love you girl"
            }
          ]
        },
        {
          "chunks": [
            {
              "chord": "A",
              "lyrics": "It's your world and I'm just passing through"
            }
          ]
        },
        {
          "chunks": [
            {
              "chord": null,
              "lyrics": "D, A, Bm, G (2 beats per chord)"
            }
          ]
        },
        {
          "chunks": [
            {
              "chord": "D",
              "lyrics": "I dig in my heels and try to slow this down"
            }
          ]
        },
        {
          "chunks": [
            {
              "chord": "A",
              "lyrics": "I want my life to revolve around"
            },
            {
              "chord": "Bm",
              "lyrics": "everything you do"
            }
          ]
        },
        {
          "chunks": [
            {
              "chord": "G",
              "lyrics": "Oh but that's all up to you"
            }
          ]
        },
        {
          "chunks": [
            {
              "chord": "D",
              "lyrics": "Everything good seems to go so fast"
            }
          ]
        },
        {
          "chunks": [
            {
              "chord": "A",
              "lyrics": "it's kinda like one big party crash"
            }
          ]
        },
        {
          "chunks": [
            {
              "chord": "Bm",
              "lyrics": "you weren't counting on"
            }
          ]
        },
        {
          "chunks": [
            {
              "chord": "G",
              "lyrics": "one day your here you're gone"
            },
            {
              "chord": "G",
              "lyrics": ""
            },
            {
              "chord": "G/F#",
              "lyrics": ""
            }
          ]
        },
        {
          "chunks": [
            {
              "chord": "Bm",
              "lyrics": "baby all I wanna do is lay right here"
            }
          ]
        },
        {
          "chunks": [
            {
              "chord": "G",
              "lyrics": "and hope it all don't"
            },
            {
              "chord": "A",
              "lyrics": "disappear"
            }
          ]
        },
        {
          "chunks": [
            {
              "chord": "D",
              "lyrics": "It's your world and I'm just in it"
            }
          ]
        },
        {
          "chunks": [
            {
              "chord": "A",
              "lyrics": "Aint no other way to spin it,"
            }
          ]
        },
        {
          "chunks": [
            {
              "chord": "Bm",
              "lyrics": "Lucky me just being there when I get to ho"
            },
            {
              "chord": "G",
              "lyrics": "ld you"
            }
          ]
        },
        {
          "chunks": [
            {
              "chord": "Bm",
              "lyrics": "I'm just here to love you girl"
            }
          ]
        },
        {
          "chunks": [
            {
              "chord": "A",
              "lyrics": "It's your world and I'm just passing through"
            }
          ]
        },
        {
          "chunks": [
            {
              "chord": null,
              "lyrics": "Solo (or play D A Bm G for a full measure each this time)"
            }
          ]
        },
        {
          "chunks": [
            {
              "chord": "D",
              "lyrics": "It's your world and I'm just in it"
            }
          ]
        },
        {
          "chunks": [
            {
              "chord": "A",
              "lyrics": "Aint no other way to spin it,"
            }
          ]
        },
        {
          "chunks": [
            {
              "chord": "Bm",
              "lyrics": "Lucky me just being there when I get to ho"
            },
            {
              "chord": "G",
              "lyrics": "ld you"
            }
          ]
        },
        {
          "chunks": [
            {
              "chord": "Bm",
              "lyrics": "I'm just here to love you girl"
            }
          ]
        },
        {
          "chunks": [
            {
              "chord": "A",
              "lyrics": "It's your world and I'm just passing through"
            }
          ]
        },
        {
          "chunks": [
            {
              "chord": null,
              "lyrics": "Riff"
            }
          ]
        },
        {
          "chunks": [
            {
              "chord": "Bm",
              "lyrics": "I'm just here to love you girl"
            }
          ]
        },
        {
          "chunks": [
            {
              "chord": "A",
              "lyrics": "It's your world and I'm just passing through"
            }
          ]
        },
        {
          "chunks": [
            {
              "chord": null,
              "lyrics": "Replay intro (same chord progression as before)"
            }
          ]
        }
      ]
    }
  ]
}
