{
  "url": "https://www.chordie.com/chord.pere/www.xguitar.com/guitar-tabs/radiohead/the_bends/high_and_dry.txt",
  "title": "High And Dry",
  "artist": "Radiohead",
  "key": null,
  "scrapedAt": "2026-02-14T10:24:21.156Z",
  "sections": [
    {
      "name": "Verse",
      "lines": [
        {
          "chunks": [
            {
              "chord": null,
              "lyrics": "OR"
            }
          ]
        },
        {
          "chunks": [
            {
              "chord": "B/F#",
              "lyrics": "two jumps in a week i bet you"
            },
            {
              "chord": "A",
              "lyrics": "think that's pretty clever don't"
            },
            {
              "chord": "E",
              "lyrics": "you boy."
            },
            {
              "chord": "E",
              "lyrics": ""
            }
          ]
        },
        {
          "chunks": [
            {
              "chord": "B/F#",
              "lyrics": "flying on your motorcycle."
            },
            {
              "chord": "A",
              "lyrics": "watching all the ground beneath"
            },
            {
              "chord": "E",
              "lyrics": "you drop."
            },
            {
              "chord": "E",
              "lyrics": ""
            }
          ]
        },
        {
          "chunks": [
            {
              "chord": null,
              "lyrics": "you'd"
            },
            {
              "chord": "B/F#",
              "lyrics": "kill yourself for recognition."
            },
            {
              "chord": "A",
              "lyrics": "kill yourself to never ev"
            },
            {
              "chord": "E",
              "lyrics": "er stop."
            },
            {
              "chord": "E",
              "lyrics": ""
            }
          ]
        },
        {
          "chunks": [
            {
              "chord": null,
              "lyrics": "you"
            },
            {
              "chord": "B/F#",
              "lyrics": "broke another mirror. you're"
            },
            {
              "chord": "A",
              "lyrics": "turning into something you"
            },
            {
              "chord": "E",
              "lyrics": "are not."
            },
            {
              "chord": "E",
              "lyrics": ""
            }
          ]
        },
        {
          "chunks": [
            {
              "chord": null,
              "lyrics": "don't lead me"
            },
            {
              "chord": "B/F#",
              "lyrics": "high,"
            },
            {
              "chord": "A",
              "lyrics": "don't lead me"
            },
            {
              "chord": "E",
              "lyrics": "dry,"
            },
            {
              "chord": "E",
              "lyrics": ""
            }
          ]
        },
        {
          "chunks": [
            {
              "chord": null,
              "lyrics": "don't lead me"
            },
            {
              "chord": "B/F#",
              "lyrics": "high,"
            },
            {
              "chord": "A",
              "lyrics": "don't lead me"
            },
            {
              "chord": "E",
              "lyrics": "dry."
            },
            {
              "chord": "E",
              "lyrics": ""
            }
          ]
        },
        {
          "chunks": [
            {
              "chord": "B/F#",
              "lyrics": ""
            },
            {
              "chord": "A",
              "lyrics": ""
            },
            {
              "chord": "E",
              "lyrics": ""
            },
            {
              "chord": "E",
              "lyrics": ""
            },
            {
              "chord": "B/F#",
              "lyrics": "drying up in conversation"
            },
            {
              "chord": "A",
              "lyrics": "you will be the one who can"
            },
            {
              "chord": "E",
              "lyrics": "not talk."
            },
            {
              "chord": "E",
              "lyrics": ""
            }
          ]
        },
        {
          "chunks": [
            {
              "chord": "B/F#",
              "lyrics": "all your insides fall to pieces."
            },
            {
              "chord": "A",
              "lyrics": "you just sit there wishing you could"
            },
            {
              "chord": "E",
              "lyrics": "still"
            },
            {
              "chord": "E",
              "lyrics": "make love."
            }
          ]
        },
        {
          "chunks": [
            {
              "chord": "B/F#",
              "lyrics": "they're the ones who'll hate you when you"
            },
            {
              "chord": "A",
              "lyrics": "think you've got the world all"
            },
            {
              "chord": "E",
              "lyrics": "sus"
            },
            {
              "chord": "E",
              "lyrics": "sed out."
            }
          ]
        },
        {
          "chunks": [
            {
              "chord": "B/F#",
              "lyrics": "they're the ones who'll spit at you."
            },
            {
              "chord": "A",
              "lyrics": "you will be the one screa"
            },
            {
              "chord": "E",
              "lyrics": "ming out."
            },
            {
              "chord": "E",
              "lyrics": ""
            }
          ]
        },
        {
          "chunks": [
            {
              "chord": null,
              "lyrics": "don't lead me"
            },
            {
              "chord": "B/F#",
              "lyrics": "high,"
            },
            {
              "chord": "A",
              "lyrics": "don't lead me"
            },
            {
              "chord": "E",
              "lyrics": "dry,"
            },
            {
              "chord": "E",
              "lyrics": ""
            }
          ]
        },
        {
          "chunks": [
            {
              "chord": null,
              "lyrics": "don't lead me"
            },
            {
              "chord": "B/F#",
              "lyrics": "high,"
            },
            {
              "chord": "A",
              "lyrics": "don't lead me"
            },
            {
              "chord": "E",
              "lyrics": "dry."
            },
            {
              "chord": "E",
              "lyrics": ""
            }
          ]
        },
        {
          "chunks": [
            {
              "chord": "B/F#",
              "lyrics": ""
            },
            {
              "chord": "A",
              "lyrics": ""
            },
            {
              "chord": "E",
              "lyrics": ""
            },
            {
              "chord": "E",
              "lyrics": ""
            },
            {
              "chord": "B/F#",
              "lyrics": ""
            },
            {
              "chord": "A",
              "lyrics": ""
            },
            {
              "chord": "E",
              "lyrics": ""
            },
            {
              "chord": "E",
              "lyrics": "it's the"
            },
            {
              "chord": "B/F#",
              "lyrics": "best thing that you ever had."
            },
            {
              "chord": "A",
              "lyrics": "the"
            },
            {
              "chord": "E",
              "lyrics": "best thing that you ever"
            },
            {
              "chord": "E",
              "lyrics": "ever had."
            }
          ]
        },
        {
          "chunks": [
            {
              "chord": null,
              "lyrics": "it's the"
            },
            {
              "chord": "B/F#",
              "lyrics": "best thing that you ever had."
            },
            {
              "chord": "A",
              "lyrics": "the"
            },
            {
              "chord": "E",
              "lyrics": "best thing that you had has"
            },
            {
              "chord": "E",
              "lyrics": "gone away."
            }
          ]
        },
        {
          "chunks": [
            {
              "chord": null,
              "lyrics": "don't lead me"
            },
            {
              "chord": "B/F#",
              "lyrics": "high,"
            },
            {
              "chord": "A",
              "lyrics": "don't lead me"
            },
            {
              "chord": "E",
              "lyrics": "dry,"
            },
            {
              "chord": "E",
              "lyrics": ""
            }
          ]
        },
        {
          "chunks": [
            {
              "chord": null,
              "lyrics": "don't lead me"
            },
            {
              "chord": "B/F#",
              "lyrics": "high,"
            },
            {
              "chord": "A",
              "lyrics": "don't lead me"
            },
            {
              "chord": "E",
              "lyrics": "dry."
            },
            {
              "chord": "E",
              "lyrics": ""
            }
          ]
        },
        {
          "chunks": [
            {
              "chord": null,
              "lyrics": "don't lead me"
            },
            {
              "chord": "B/F#",
              "lyrics": "high,"
            },
            {
              "chord": "A",
              "lyrics": ""
            },
            {
              "chord": "E",
              "lyrics": ""
            },
            {
              "chord": "E",
              "lyrics": ""
            }
          ]
        },
        {
          "chunks": [
            {
              "chord": null,
              "lyrics": "don't lead me"
            },
            {
              "chord": "B/F#",
              "lyrics": "high,"
            },
            {
              "chord": "A",
              "lyrics": "don't leave me"
            },
            {
              "chord": "E",
              "lyrics": "dry."
            }
          ]
        },
        {
          "chunks": [
            {
              "chord": null,
              "lyrics": "Solo: (on a single string)"
            }
          ]
        },
        {
          "chunks": [
            {
              "chord": null,
              "lyrics": "HIGH AND DRY:"
            }
          ]
        },
        {
          "chunks": [
            {
              "chord": null,
              "lyrics": "i noticed there are some lines wrong:"
            }
          ]
        },
        {
          "chunks": [
            {
              "chord": null,
              "lyrics": "it's the"
            },
            {
              "chord": "B/F#",
              "lyrics": "best thing that you ever had"
            },
            {
              "chord": "A",
              "lyrics": ". the"
            },
            {
              "chord": "E",
              "lyrics": "best thing that you ever"
            },
            {
              "chord": "E",
              "lyrics": "ever had."
            }
          ]
        },
        {
          "chunks": [
            {
              "chord": null,
              "lyrics": "it's the"
            },
            {
              "chord": "B/F#",
              "lyrics": "best thing that you ever had."
            },
            {
              "chord": "A",
              "lyrics": "the"
            },
            {
              "chord": "E",
              "lyrics": "best thing that you had has"
            },
            {
              "chord": "E",
              "lyrics": "gone away."
            }
          ]
        },
        {
          "chunks": [
            {
              "chord": null,
              "lyrics": "While the right chords here are the followings:"
            }
          ]
        },
        {
          "chunks": [
            {
              "chord": "B/F#",
              "lyrics": ""
            },
            {
              "chord": "A",
              "lyrics": ""
            },
            {
              "chord": "E",
              "lyrics": ""
            },
            {
              "chord": "E",
              "lyrics": "it's the best thing that you ever had. the best thing that you ever ever had."
            }
          ]
        },
        {
          "chunks": [
            {
              "chord": "B/F#",
              "lyrics": ""
            },
            {
              "chord": "A",
              "lyrics": ""
            },
            {
              "chord": "E",
              "lyrics": ""
            },
            {
              "chord": "E",
              "lyrics": "it's the best thing that you ever had. the best thing that you had has gone away."
            }
          ]
        },
        {
          "chunks": [
            {
              "chord": null,
              "lyrics": "Then, along all the song, the second E is actually an A/E (04x200), except before the chorus when it's Esus4 (\"...into something (E) you are (Esus4) not..). Try also to change the B/F# into a F#11-."
            }
          ]
        },
        {
          "chunks": [
            {
              "chord": null,
              "lyrics": "bye, Marcello"
            }
          ]
        }
      ]
    }
  ]
}
