{
  "url": "https://www.chordie.com/chord.pere/www.xguitar.com/guitar-tabs/blur/leisure/bad_day.txt",
  "title": "Bad Day",
  "artist": "Blur",
  "key": null,
  "scrapedAt": "2025-12-16T13:56:54.028Z",
  "sections": [
    {
      "name": "Verse",
      "lines": [
        {
          "chunks": [
            {
              "chord": null,
              "lyrics": "(intro)"
            }
          ]
        },
        {
          "chunks": [
            {
              "chord": "D",
              "lyrics": ""
            }
          ]
        },
        {
          "chunks": [
            {
              "chord": "D",
              "lyrics": "Do you do anything you do?"
            }
          ]
        },
        {
          "chunks": [
            {
              "chord": "C",
              "lyrics": "No"
            },
            {
              "chord": "A",
              "lyrics": "she"
            },
            {
              "chord": "D",
              "lyrics": "said"
            },
            {
              "chord": "A",
              "lyrics": ""
            }
          ]
        },
        {
          "chunks": [
            {
              "chord": "D",
              "lyrics": "Do you want anything you ever wanted?"
            }
          ]
        },
        {
          "chunks": [
            {
              "chord": "C",
              "lyrics": "No"
            },
            {
              "chord": "A",
              "lyrics": "she"
            },
            {
              "chord": "D",
              "lyrics": "said"
            },
            {
              "chord": "A",
              "lyrics": ""
            }
          ]
        },
        {
          "chunks": [
            {
              "chord": null,
              "lyrics": "(fill 1)"
            }
          ]
        },
        {
          "chunks": [
            {
              "chord": null,
              "lyrics": "e ------------------"
            }
          ]
        },
        {
          "chunks": [
            {
              "chord": null,
              "lyrics": "B ------------------"
            }
          ]
        },
        {
          "chunks": [
            {
              "chord": null,
              "lyrics": "G --5-4-2-0---------"
            }
          ]
        },
        {
          "chunks": [
            {
              "chord": null,
              "lyrics": "D ----------3--4-5--"
            }
          ]
        },
        {
          "chunks": [
            {
              "chord": null,
              "lyrics": "A ------------------"
            }
          ]
        },
        {
          "chunks": [
            {
              "chord": null,
              "lyrics": "E ------------------"
            }
          ]
        },
        {
          "chunks": [
            {
              "chord": null,
              "lyrics": "(fill 2)"
            }
          ]
        },
        {
          "chunks": [
            {
              "chord": null,
              "lyrics": "e -------------"
            }
          ]
        },
        {
          "chunks": [
            {
              "chord": null,
              "lyrics": "B -------------"
            }
          ]
        },
        {
          "chunks": [
            {
              "chord": null,
              "lyrics": "G ---h-p-------"
            }
          ]
        },
        {
          "chunks": [
            {
              "chord": null,
              "lyrics": "D --5-7-5-7-5--"
            }
          ]
        },
        {
          "chunks": [
            {
              "chord": null,
              "lyrics": "A -------------"
            }
          ]
        },
        {
          "chunks": [
            {
              "chord": null,
              "lyrics": "E -------------"
            }
          ]
        },
        {
          "chunks": [
            {
              "chord": "D",
              "lyrics": "She"
            },
            {
              "chord": "A",
              "lyrics": "don't know"
            },
            {
              "chord": "D",
              "lyrics": "how"
            }
          ]
        },
        {
          "chunks": [
            {
              "chord": "A",
              "lyrics": "How to"
            },
            {
              "chord": "D",
              "lyrics": "feel"
            }
          ]
        },
        {
          "chunks": [
            {
              "chord": "A",
              "lyrics": "This is a"
            },
            {
              "chord": "D",
              "lyrics": "bad day"
            }
          ]
        },
        {
          "chunks": [
            {
              "chord": "A",
              "lyrics": "This is a"
            },
            {
              "chord": "D",
              "lyrics": "bad day"
            }
          ]
        },
        {
          "chunks": [
            {
              "chord": "C",
              "lyrics": "know"
            }
          ]
        },
        {
          "chunks": [
            {
              "chord": null,
              "lyrics": "fill 3"
            }
          ]
        },
        {
          "chunks": [
            {
              "chord": null,
              "lyrics": "e ---------------------"
            }
          ]
        },
        {
          "chunks": [
            {
              "chord": null,
              "lyrics": "B ---------------------"
            }
          ]
        },
        {
          "chunks": [
            {
              "chord": null,
              "lyrics": "G ----------0---0---2--"
            }
          ]
        },
        {
          "chunks": [
            {
              "chord": null,
              "lyrics": "D --------2---2---0----"
            }
          ]
        },
        {
          "chunks": [
            {
              "chord": null,
              "lyrics": "A ------3--------------"
            }
          ]
        },
        {
          "chunks": [
            {
              "chord": null,
              "lyrics": "E --5-7----------------"
            }
          ]
        },
        {
          "chunks": [
            {
              "chord": "D",
              "lyrics": "Do you have anything you ever had?"
            }
          ]
        },
        {
          "chunks": [
            {
              "chord": "C",
              "lyrics": "No"
            },
            {
              "chord": "A",
              "lyrics": "she"
            },
            {
              "chord": "D",
              "lyrics": "said"
            },
            {
              "chord": "A",
              "lyrics": ""
            }
          ]
        },
        {
          "chunks": [
            {
              "chord": "D",
              "lyrics": "Do you love anyone you ever loved?"
            }
          ]
        },
        {
          "chunks": [
            {
              "chord": "C",
              "lyrics": ""
            },
            {
              "chord": "A",
              "lyrics": ""
            },
            {
              "chord": "D",
              "lyrics": ""
            },
            {
              "chord": "A",
              "lyrics": ""
            }
          ]
        },
        {
          "chunks": [
            {
              "chord": null,
              "lyrics": "Yes she said"
            }
          ]
        },
        {
          "chunks": [
            {
              "chord": null,
              "lyrics": "(middle 4x)"
            }
          ]
        },
        {
          "chunks": [
            {
              "chord": null,
              "lyrics": "e ---------------------------"
            }
          ]
        },
        {
          "chunks": [
            {
              "chord": null,
              "lyrics": "B ---------------------------"
            }
          ]
        },
        {
          "chunks": [
            {
              "chord": null,
              "lyrics": "G ---------------------------"
            }
          ]
        },
        {
          "chunks": [
            {
              "chord": null,
              "lyrics": "D --4---4---5---5---5---5----"
            }
          ]
        },
        {
          "chunks": [
            {
              "chord": null,
              "lyrics": "A ----5---5---4---4---4---4--"
            }
          ]
        },
        {
          "chunks": [
            {
              "chord": null,
              "lyrics": "E ---------------------------"
            }
          ]
        },
        {
          "chunks": [
            {
              "chord": null,
              "lyrics": "This is to feel lost in your world"
            }
          ]
        },
        {
          "chunks": [
            {
              "chord": null,
              "lyrics": "(solo)"
            }
          ]
        },
        {
          "chunks": [
            {
              "chord": null,
              "lyrics": "e ---------------p-------- --------------p-----p-----"
            }
          ]
        },
        {
          "chunks": [
            {
              "chord": null,
              "lyrics": "B --------------8-6----6-- -------------8-6---8-6----"
            }
          ]
        },
        {
          "chunks": [
            {
              "chord": null,
              "lyrics": "G --7-5---p--5------77---- --7-5--p--5------7-----7--"
            }
          ]
        },
        {
          "chunks": [
            {
              "chord": null,
              "lyrics": "D -------7-5-3------------ (3x) ------7-5-3---------------"
            }
          ]
        },
        {
          "chunks": [
            {
              "chord": null,
              "lyrics": "A ------------------------ --------------------------"
            }
          ]
        },
        {
          "chunks": [
            {
              "chord": null,
              "lyrics": "E ------------------------ --------------------------"
            }
          ]
        }
      ]
    }
  ]
}
