{
  "url": "https://www.chordie.com/chord.pere/www.azchords.com/a/acefrehley-tabs-21546/doya-tabs-205924.html",
  "title": "Do Ya",
  "artist": "Ace Frehley",
  "key": null,
  "scrapedAt": "2025-12-17T00:21:12.835Z",
  "sections": [
    {
      "name": "Verse",
      "lines": [
        {
          "chunks": [
            {
              "chord": null,
              "lyrics": "Tune down 1/2 step"
            }
          ]
        },
        {
          "chunks": [
            {
              "chord": null,
              "lyrics": "/ = slide up"
            }
          ]
        },
        {
          "chunks": [
            {
              "chord": null,
              "lyrics": "\\ = slide down"
            }
          ]
        },
        {
          "chunks": [
            {
              "chord": null,
              "lyrics": "b = bend (the number of parentheses is the number of steps)"
            }
          ]
        },
        {
          "chunks": [
            {
              "chord": null,
              "lyrics": "pb = pre-bend"
            }
          ]
        },
        {
          "chunks": [
            {
              "chord": null,
              "lyrics": "r = release bend"
            }
          ]
        },
        {
          "chunks": [
            {
              "chord": null,
              "lyrics": "^ = legato (hammer-ons and pull-offs)"
            }
          ]
        },
        {
          "chunks": [
            {
              "chord": null,
              "lyrics": "Intro:"
            }
          ]
        },
        {
          "chunks": [
            {
              "chord": null,
              "lyrics": "D5 A5 G5 <-- play 4 times"
            }
          ]
        },
        {
          "chunks": [
            {
              "chord": null,
              "lyrics": "After the 1st and 3rd repeat, play the following with a slide:"
            }
          ]
        },
        {
          "chunks": [
            {
              "chord": null,
              "lyrics": "-12\\--"
            }
          ]
        },
        {
          "chunks": [
            {
              "chord": null,
              "lyrics": "-12\\--"
            }
          ]
        },
        {
          "chunks": [
            {
              "chord": null,
              "lyrics": "After the 4th repeat, play this:"
            }
          ]
        },
        {
          "chunks": [
            {
              "chord": null,
              "lyrics": "Verse:"
            }
          ]
        },
        {
          "chunks": [
            {
              "chord": null,
              "lyrics": "Well"
            },
            {
              "chord": "D5",
              "lyrics": "in this"
            },
            {
              "chord": "A5",
              "lyrics": "life I've seen"
            },
            {
              "chord": "G5",
              "lyrics": "everything"
            }
          ]
        },
        {
          "chunks": [
            {
              "chord": null,
              "lyrics": "I can see"
            },
            {
              "chord": "A5",
              "lyrics": "woman"
            }
          ]
        },
        {
          "chunks": [
            {
              "chord": null,
              "lyrics": "Use same chord pattern unless otherwise noted:"
            }
          ]
        },
        {
          "chunks": [
            {
              "chord": null,
              "lyrics": "I've seen lovers flying thru the air"
            }
          ]
        },
        {
          "chunks": [
            {
              "chord": null,
              "lyrics": "Hand in hand"
            }
          ]
        },
        {
          "chunks": [
            {
              "chord": null,
              "lyrics": "I've seen babies dancing in the midnight sun"
            }
          ]
        },
        {
          "chunks": [
            {
              "chord": null,
              "lyrics": "And I've seen dreams come from the heavenly skies above"
            }
          ]
        },
        {
          "chunks": [
            {
              "chord": null,
              "lyrics": "I've seen old men crying"
            }
          ]
        },
        {
          "chunks": [
            {
              "chord": null,
              "lyrics": "At their own grave sites and"
            }
          ]
        },
        {
          "chunks": [
            {
              "chord": null,
              "lyrics": "I've seen pigs all sittin'"
            }
          ]
        },
        {
          "chunks": [
            {
              "chord": "G5",
              "lyrics": "Watching picture slides"
            }
          ]
        },
        {
          "chunks": [
            {
              "chord": null,
              "lyrics": "G5 * G5"
            }
          ]
        },
        {
          "chunks": [
            {
              "chord": null,
              "lyrics": "But I ain't never seen nothin' like you"
            }
          ]
        },
        {
          "chunks": [
            {
              "chord": null,
              "lyrics": "-12\\--"
            }
          ]
        },
        {
          "chunks": [
            {
              "chord": null,
              "lyrics": "-12\\--"
            }
          ]
        },
        {
          "chunks": [
            {
              "chord": null,
              "lyrics": "Chorus:"
            }
          ]
        },
        {
          "chunks": [
            {
              "chord": "D5",
              "lyrics": "Do ya do ya"
            },
            {
              "chord": "A5",
              "lyrics": "want my"
            },
            {
              "chord": "G5",
              "lyrics": "love w"
            },
            {
              "chord": "A5",
              "lyrics": "oman"
            }
          ]
        },
        {
          "chunks": [
            {
              "chord": null,
              "lyrics": "Use same chord pattern unless otherwise noted:"
            }
          ]
        },
        {
          "chunks": [
            {
              "chord": null,
              "lyrics": "Do ya do ya want my face"
            }
          ]
        },
        {
          "chunks": [
            {
              "chord": null,
              "lyrics": "I need it"
            }
          ]
        },
        {
          "chunks": [
            {
              "chord": null,
              "lyrics": "Do ya do ya want my mind"
            }
          ]
        },
        {
          "chunks": [
            {
              "chord": null,
              "lyrics": "I'm sayin'"
            }
          ]
        },
        {
          "chunks": [
            {
              "chord": null,
              "lyrics": "Do ya do ya want my love"
            }
          ]
        },
        {
          "chunks": [
            {
              "chord": null,
              "lyrics": "Verse:"
            }
          ]
        },
        {
          "chunks": [
            {
              "chord": null,
              "lyrics": "Well I've heard the crowd singin' outta tune"
            }
          ]
        },
        {
          "chunks": [
            {
              "chord": null,
              "lyrics": "As they sang Auld Lang Syne"
            }
          ]
        },
        {
          "chunks": [
            {
              "chord": null,
              "lyrics": "By the light of the moon"
            }
          ]
        },
        {
          "chunks": [
            {
              "chord": null,
              "lyrics": "And I heard preachers banging"
            }
          ]
        },
        {
          "chunks": [
            {
              "chord": null,
              "lyrics": "On their drums"
            }
          ]
        },
        {
          "chunks": [
            {
              "chord": null,
              "lyrics": "And I heard police playing with their guns"
            }
          ]
        },
        {
          "chunks": [
            {
              "chord": null,
              "lyrics": "But I ain't never heard nothin' like you"
            }
          ]
        },
        {
          "chunks": [
            {
              "chord": null,
              "lyrics": "Bridge:"
            }
          ]
        },
        {
          "chunks": [
            {
              "chord": null,
              "lyrics": "Gtr. 1 (clean) (with variations on repeat)"
            }
          ]
        },
        {
          "chunks": [
            {
              "chord": null,
              "lyrics": "|"
            }
          ]
        },
        {
          "chunks": [
            {
              "chord": null,
              "lyrics": "| Gtr. 2 (dirty)"
            }
          ]
        },
        {
          "chunks": [
            {
              "chord": "D",
              "lyrics": "In the coun"
            },
            {
              "chord": "Dsus4",
              "lyrics": "try wh"
            },
            {
              "chord": "D",
              "lyrics": "ere the"
            },
            {
              "chord": "Asus4",
              "lyrics": "sky touches"
            },
            {
              "chord": "A",
              "lyrics": "down"
            }
          ]
        },
        {
          "chunks": [
            {
              "chord": "Gsus4",
              "lyrics": "On the field she lay her"
            },
            {
              "chord": "G",
              "lyrics": "down to rest"
            }
          ]
        },
        {
          "chunks": [
            {
              "chord": null,
              "lyrics": "(play the arpeggiated figure)"
            }
          ]
        },
        {
          "chunks": [
            {
              "chord": null,
              "lyrics": "In the waterside"
            }
          ]
        },
        {
          "chunks": [
            {
              "chord": null,
              "lyrics": "Use same chord pattern:"
            }
          ]
        },
        {
          "chunks": [
            {
              "chord": null,
              "lyrics": "They come a-runnin' just to get a look"
            }
          ]
        },
        {
          "chunks": [
            {
              "chord": null,
              "lyrics": "Just to feel, to touch her long black hair"
            }
          ]
        },
        {
          "chunks": [
            {
              "chord": null,
              "lyrics": "They don't give a damn"
            }
          ]
        },
        {
          "chunks": [
            {
              "chord": null,
              "lyrics": "After another chorus, play this fill w/ a slide:"
            }
          ]
        },
        {
          "chunks": [
            {
              "chord": null,
              "lyrics": "(I don't think this is actually right)"
            }
          ]
        },
        {
          "chunks": [
            {
              "chord": null,
              "lyrics": "Verse:"
            }
          ]
        },
        {
          "chunks": [
            {
              "chord": null,
              "lyrics": "I think you know what I'm tryin' to say woman"
            }
          ]
        },
        {
          "chunks": [
            {
              "chord": null,
              "lyrics": "That is I'd like to save you for a rainy day"
            }
          ]
        },
        {
          "chunks": [
            {
              "chord": null,
              "lyrics": "I've seen enough of this world to know that I've gotta"
            }
          ]
        },
        {
          "chunks": [
            {
              "chord": null,
              "lyrics": "Gotta get it all, get it all to (???)"
            }
          ]
        },
        {
          "chunks": [
            {
              "chord": null,
              "lyrics": "After the last chorus, play these outro chords:"
            }
          ]
        },
        {
          "chunks": [
            {
              "chord": null,
              "lyrics": "C5 C5/B(?) Bb5 G5"
            }
          ]
        },
        {
          "chunks": [
            {
              "chord": null,
              "lyrics": "C5 Bb5(?) G5"
            }
          ]
        },
        {
          "chunks": [
            {
              "chord": null,
              "lyrics": "Outro solo (approximation):"
            }
          ]
        }
      ]
    }
  ]
}
