{
  "url": "https://www.chordie.com/chord.pere/www.guitartabs.cc/tabs/b/bob_welch/ebony_eyes_tab.html",
  "title": "Ebony Eyes",
  "artist": "Bob Welch",
  "key": null,
  "scrapedAt": "2025-12-17T06:38:20.851Z",
  "sections": [
    {
      "name": "Verse",
      "lines": [
        {
          "chunks": [
            {
              "chord": null,
              "lyrics": "By Bob Welch"
            }
          ]
        },
        {
          "chunks": [
            {
              "chord": null,
              "lyrics": "From the FRENCH KISS album, 1977"
            }
          ]
        },
        {
          "chunks": [
            {
              "chord": null,
              "lyrics": "Bob Welch was one of the great guitarists to find their way through the"
            }
          ]
        },
        {
          "chunks": [
            {
              "chord": null,
              "lyrics": "Fleetwood Mac family. He was the guitarist right before Lindsey Buckingham."
            }
          ]
        },
        {
          "chunks": [
            {
              "chord": null,
              "lyrics": "Along with Christine McVie he wrote the hit Hypnotized. He is also responsible"
            }
          ]
        },
        {
          "chunks": [
            {
              "chord": null,
              "lyrics": "for Sentimental Lady (you can find that tab with the Fleetwood Mac stuff)."
            }
          ]
        },
        {
          "chunks": [
            {
              "chord": null,
              "lyrics": "Mystery Train was another hit penned for Fleetwood Mac by Bob Welch. French"
            }
          ]
        },
        {
          "chunks": [
            {
              "chord": null,
              "lyrics": "Kiss was his solo effort after leaving the band. It contains a memorable little riff."
            }
          ]
        },
        {
          "chunks": [
            {
              "chord": null,
              "lyrics": "Tuning: Standard"
            }
          ]
        },
        {
          "chunks": [
            {
              "chord": null,
              "lyrics": "Chords used in this song are Am Dm E C"
            }
          ]
        },
        {
          "chunks": [
            {
              "chord": null,
              "lyrics": "Am 0 Dm 1 E 0 C 0"
            }
          ]
        },
        {
          "chunks": [
            {
              "chord": null,
              "lyrics": "1 2 0 1"
            }
          ]
        },
        {
          "chunks": [
            {
              "chord": null,
              "lyrics": "2 3 1 0"
            }
          ]
        },
        {
          "chunks": [
            {
              "chord": null,
              "lyrics": "2 0 2 2"
            }
          ]
        },
        {
          "chunks": [
            {
              "chord": null,
              "lyrics": "0 X 2 3"
            }
          ]
        },
        {
          "chunks": [
            {
              "chord": null,
              "lyrics": "X X 0 X"
            }
          ]
        },
        {
          "chunks": [
            {
              "chord": null,
              "lyrics": "THE MEMORABLE RIFF: (play 4 times at beginning of song)"
            }
          ]
        },
        {
          "chunks": [
            {
              "chord": "Am",
              "lyrics": "Have you seen that girl in the"
            },
            {
              "chord": "E",
              "lyrics": "corner?"
            }
          ]
        },
        {
          "chunks": [
            {
              "chord": null,
              "lyrics": "I'd like to"
            },
            {
              "chord": "Am",
              "lyrics": "take her out of her c"
            },
            {
              "chord": "E",
              "lyrics": "hains"
            }
          ]
        },
        {
          "chunks": [
            {
              "chord": null,
              "lyrics": "'Cause if I"
            },
            {
              "chord": "Am",
              "lyrics": "had my ways with you"
            },
            {
              "chord": "E",
              "lyrics": "baby"
            }
          ]
        },
        {
          "chunks": [
            {
              "chord": null,
              "lyrics": "I would be ch"
            },
            {
              "chord": "Dm",
              "lyrics": "anging your life t"
            },
            {
              "chord": "Am",
              "lyrics": "oday"
            }
          ]
        },
        {
          "chunks": [
            {
              "chord": null,
              "lyrics": "(chorus):"
            }
          ]
        },
        {
          "chunks": [
            {
              "chord": "C",
              "lyrics": "Your eyes got me d"
            },
            {
              "chord": "Am",
              "lyrics": "reamin'"
            }
          ]
        },
        {
          "chunks": [
            {
              "chord": "C",
              "lyrics": "Your eyes got me b"
            },
            {
              "chord": "Am",
              "lyrics": "lind"
            }
          ]
        },
        {
          "chunks": [
            {
              "chord": "C",
              "lyrics": "Your eyes got me h"
            },
            {
              "chord": "Am",
              "lyrics": "opin'"
            }
          ]
        },
        {
          "chunks": [
            {
              "chord": null,
              "lyrics": "Dm Riff/Am"
            }
          ]
        },
        {
          "chunks": [
            {
              "chord": null,
              "lyrics": "That I'll be holding you close tonight"
            }
          ]
        },
        {
          "chunks": [
            {
              "chord": null,
              "lyrics": "repeat chorus"
            }
          ]
        },
        {
          "chunks": [
            {
              "chord": null,
              "lyrics": "She was the"
            },
            {
              "chord": "Am",
              "lyrics": "same as a hundred l"
            },
            {
              "chord": "E",
              "lyrics": "adies"
            }
          ]
        },
        {
          "chunks": [
            {
              "chord": null,
              "lyrics": "But when my e"
            },
            {
              "chord": "Am",
              "lyrics": "yes looked at her I l"
            },
            {
              "chord": "E",
              "lyrics": "earned"
            }
          ]
        },
        {
          "chunks": [
            {
              "chord": null,
              "lyrics": "that she was"
            },
            {
              "chord": "Am",
              "lyrics": "keeping a secret f"
            },
            {
              "chord": "E",
              "lyrics": "ire"
            }
          ]
        },
        {
          "chunks": [
            {
              "chord": null,
              "lyrics": "and if I"
            },
            {
              "chord": "Dm",
              "lyrics": "got too close I'd b"
            },
            {
              "chord": "Am",
              "lyrics": "urn"
            }
          ]
        },
        {
          "chunks": [
            {
              "chord": null,
              "lyrics": "N/C Am E"
            }
          ]
        },
        {
          "chunks": [
            {
              "chord": null,
              "lyrics": "So it looked like I'd have to move slowly"
            }
          ]
        },
        {
          "chunks": [
            {
              "chord": null,
              "lyrics": "Just like a c"
            },
            {
              "chord": "Am",
              "lyrics": "at at night in the t"
            },
            {
              "chord": "E",
              "lyrics": "rees"
            }
          ]
        },
        {
          "chunks": [
            {
              "chord": null,
              "lyrics": "'cause I was w"
            },
            {
              "chord": "Am",
              "lyrics": "aiting for her to s"
            },
            {
              "chord": "E",
              "lyrics": "how me"
            }
          ]
        },
        {
          "chunks": [
            {
              "chord": null,
              "lyrics": "That way that"
            },
            {
              "chord": "Dm",
              "lyrics": "she liked her love to"
            },
            {
              "chord": "Am",
              "lyrics": "feel"
            }
          ]
        },
        {
          "chunks": [
            {
              "chord": null,
              "lyrics": "repeat chorus"
            }
          ]
        },
        {
          "chunks": [
            {
              "chord": "Dm",
              "lyrics": ""
            },
            {
              "chord": "Am",
              "lyrics": "Ebony Eyes"
            }
          ]
        },
        {
          "chunks": [
            {
              "chord": "Dm",
              "lyrics": ""
            },
            {
              "chord": "Am",
              "lyrics": "Ebony Eyes"
            }
          ]
        },
        {
          "chunks": [
            {
              "chord": "Dm",
              "lyrics": ""
            },
            {
              "chord": "Am",
              "lyrics": "Ebony Eyes"
            }
          ]
        },
        {
          "chunks": [
            {
              "chord": "Dm",
              "lyrics": ""
            },
            {
              "chord": "Am",
              "lyrics": "Ebony Eyes"
            }
          ]
        },
        {
          "chunks": [
            {
              "chord": null,
              "lyrics": "play the riff as you outro the \"Ebony eyes\" bit"
            }
          ]
        }
      ]
    }
  ]
}
